vpype_perspective/__init__.py
vpype_perspective/commands.py
vpype_perspective/matrices.py
vpype_perspective/perspective.py
vpype_perspective-0.1.0.dist-info/LICENSE
vpype_perspective-0.1.0.dist-info/METADATA
vpype_perspective-0.1.0.dist-info/WHEEL
vpype_perspective-0.1.0.dist-info/entry_points.txt
vpype_perspective-0.1.0.dist-info/top_level.txt
vpype_perspective-0.1.0.dist-info/RECORD
