Metadata-Version: 2.1
Name: vpype-perspective
Version: 0.1.0
Summary: Put your art in perspective with vpype.
Home-page: https://github.com/abey79/vpype-perspective
Author: Antoine Beyeler
License: UNKNOWN
Platform: UNKNOWN
Classifier: Development Status :: 4 - Beta
Classifier: License :: OSI Approved :: MIT License
Classifier: Topic :: Multimedia :: Graphics
Classifier: Environment :: Plugins
License-File: LICENSE
Requires-Dist: click
Requires-Dist: numpy
Requires-Dist: vpype[all] (>=1.10)
